odoo/addons/product_priority/README.rst
odoo/addons/product_priority/__init__.py
odoo/addons/product_priority/__manifest__.py
odoo/addons/product_priority/i18n/ca.po
odoo/addons/product_priority/i18n/de.po
odoo/addons/product_priority/i18n/es.po
odoo/addons/product_priority/i18n/fr.po
odoo/addons/product_priority/i18n/hr.po
odoo/addons/product_priority/i18n/it.po
odoo/addons/product_priority/i18n/nl_NL.po
odoo/addons/product_priority/i18n/product_priority.pot
odoo/addons/product_priority/i18n/sl.po
odoo/addons/product_priority/models/__init__.py
odoo/addons/product_priority/models/product.py
odoo/addons/product_priority/readme/CONTRIBUTORS.rst
odoo/addons/product_priority/readme/DESCRIPTION.rst
odoo/addons/product_priority/readme/USAGE.rst
odoo/addons/product_priority/static/description/icon.png
odoo/addons/product_priority/static/description/index.html
odoo/addons/product_priority/views/product_view.xml
odoo12_addon_product_priority-12.0.1.0.0.99.dev11.dist-info/METADATA
odoo12_addon_product_priority-12.0.1.0.0.99.dev11.dist-info/WHEEL
odoo12_addon_product_priority-12.0.1.0.0.99.dev11.dist-info/top_level.txt
odoo12_addon_product_priority-12.0.1.0.0.99.dev11.dist-info/RECORD
